{
  "weapons": [
    {"name": "ПМ", "description": "Простой пистолет Макарова. Надёжный, но слабый.", "price": 50, "attack": 15, "weight": 0.8},
    {"name": "ТТ", "description": "Пистолет Токарева. Мощнее ПМ, но ненадёжен.", "price": 70, "attack": 20, "weight": 0.9},
    {"name": "Глок", "description": "Австрийский пистолет. Точный и современный.", "price": 120, "attack": 25, "weight": 0.7},
    {"name": "Удав", "description": "Российский пистолет-пулемёт. Компактный и скорострельный.", "price": 180, "attack": 22, "weight": 0.65},
    {"name": "АК-74", "description": "Автомат Калашникова. Хорошая огневая мощь.", "price": 200, "attack": 35, "weight": 3.5},
    {"name": "М4А1", "description": "Американский карабин. Точный и лёгкий.", "price": 220, "attack": 38, "weight": 3.0},
    {"name": "СВД", "description": "Снайперская винтовка Драгунова. Точность на высоте.", "price": 350, "attack": 60, "weight": 4.2},
    {"name": "Винторез", "description": "Снайперская винтовка с интегрированным глушителем.", "price": 400, "attack": 70, "weight": 3.8},
    {"name": "ИЖ-27", "description": "Двуствольное охотничье ружьё. Мощный выстрел в упор.", "price": 150, "attack": 45, "weight": 3.2},
    {"name": "Сайга-12", "description": "Полуавтоматический дробовик. Быстрый огонь.", "price": 250, "attack": 40, "weight": 3.5},
    {"name": "ПКМ", "description": "Пулемёт Калашникова. Огонь на подавление.", "price": 450, "attack": 30, "weight": 7.5},
    {"name": "Нож сталкера", "description": "Простой нож. Лучше, чем ничего.", "price": 30, "attack": 10, "weight": 0.3},
    {"name": "Мачете", "description": "Длинный нож для рубки. Хорош в ближнем бою.", "price": 60, "attack": 15, "weight": 0.8},
    {"name": "Кинжал", "description": "Острый кинжал. Смертоносный в ближнем бою.", "price": 90, "attack": 20, "weight": 0.45}
  ],
  "armor": [
    {"name": "Вязаная шапка", "description": "Старая вязаная шапка. От холода, не от пуль.", "price": 10, "defense": 2, "weight": 0.2},
    {"name": "Каска", "description": "Советская каска. Лёгкая защита от осколков.", "price": 50, "defense": 8, "weight": 0.8},
    {"name": "Баллистический шлем", "description": "Современный бронешлем. Защита от пуль.", "price": 150, "defense": 20, "weight": 1.2},
    {"name": "Кожаная куртка", "description": "Стандартная кожаная куртка. Минимальная защита.", "price": 30, "defense": 5, "weight": 1.5},
    {"name": "Бронежилет", "description": "Армейский бронежилет. Средняя защита.", "price": 100, "defense": 18, "weight": 3.0},
    {"name": "Комбинезон сталкера", "description": "Спецкостюм для работы в Зоне. Хорошая защита.", "price": 300, "defense": 35, "weight": 5.0},
    {"name": "Экзоскелет", "description": "Тяжёлая броня с приводом. Максимальная защита.", "price": 600, "defense": 55, "weight": 15.0},
    {"name": "Армейские ботинки", "description": "Прочные армейские ботинки. Защита ног.", "price": 40, "defense": 8, "weight": 0.8},
    {"name": "Боевые ботинки", "description": "Бронированные ботинки. Максимум защиты.", "price": 80, "defense": 15, "weight": 1.2}
  ],
  "backpacks": [
    {"name": "Походный рюкзак", "description": "Обычный походный рюкзак. Увеличивает переносимый вес.", "price": 80, "backpack_bonus": 15, "weight": 3.0},
    {"name": "Военный рюкзак", "description": "Армейский рюкзак. Хорошая вместимость.", "price": 150, "backpack_bonus": 25, "weight": 4.0},
    {"name": "Тактический рюкзак", "description": "Современный тактический рюкзак с системой быстрого доступа.", "price": 250, "backpack_bonus": 40, "weight": 5.0},
    {"name": "Грузовой рюкзак", "description": "Большой грузовой рюкзак для перевозки тяжёлых грузов.", "price": 400, "backpack_bonus": 60, "weight": 8.0}
  ],
  "artifacts": [
    {"name": "Медуза", "description": "Светящийся артефакт. +15% к сопротивлению урону.", "price": 800, "weight": 0.5},
    {"name": "Камень", "description": "Плотный артефакт. +5 к защите.", "price": 600, "weight": 1.0},
    {"name": "Пульсатор", "description": "Пульсирующий артефакт. Тёплый на ощупь.", "price": 120, "weight": 0.3},
    {"name": "Грозовая", "description": "Искрящийся артефакт. +10% к критическому удару.", "price": 1000, "weight": 0.3},
    {"name": "Пустышка", "description": "Пустой артефакт. +5 к удаче.", "price": 500, "weight": 0.2},
    {"name": "Воронка", "description": "Артефакт в форме воронки. +20% к находкам.", "price": 1200, "weight": 0.8},
    {"name": "Слизь", "description": "Скользкий артефакт. +10 HP.", "price": 400, "weight": 0.4},
    {"name": "Пыль", "description": "Лёгкий артефакт. +5% к уклонению.", "price": 550, "weight": 0.1},
    {"name": "Фрагмент", "description": "Осколок аномалии. +5 к силе.", "price": 700, "weight": 0.6},
    {"name": "Огненник", "description": "Тёплый камень из Жарки. +10 защиты от огня, но радиоактивен.", "price": 100, "weight": 0.4},
    {"name": "Электра", "description": "Искрящийся шар из Токсичного тумана. +15 энергии.", "price": 110, "weight": 0.3},
    {"name": "Слеза", "description": "Светящаяся вода из лужи. -15 радиации.", "price": 90, "weight": 0.5},
    {"name": "Щит", "description": "Прочный кристалл. +15 защиты, но тяжёлый.", "price": 140, "weight": 0.6},
    {"name": "Бенгальский огонь", "description": "Яркий искрящийся артефакт. +15% к урону оружия.", "price": 1100, "weight": 0.3},
    {"name": "Вспышка", "description": "Мерцающий артефакт. +10% к находкам, +5 к восприятию.", "price": 900, "weight": 0.2},
    {"name": "Грави", "description": "Тяжёлый артефакт с искажающим полем. +20 к защите.", "price": 2500, "weight": 2.0},
    {"name": "Золотая рыбка", "description": "Редкий гравитационный артефакт. +15 к удаче.", "price": 3000, "weight": 0.5},
    {"name": "Ночная звезда", "description": "Мерцающий гравитационный артефакт. +10 к максимальному весу.", "price": 2200, "weight": 0.4},
    {"name": "Выверт", "description": "Нестабильный пси-артефакт. +15% к уклонению.", "price": 1800, "weight": 0.3},
    {"name": "Пузырь", "description": "Полупрозрачный пси-артефакт. +20% к сопротивлению урону.", "price": 2000, "weight": 0.4},
    {"name": "Лунный свет", "description": "Светящийся пси-артефакт. +20 к максимальной энергии.", "price": 2800, "weight": 0.2}
  ],
  "rare_artifacts": [
    {"name": "Мечта", "description": "Редчайший артефакт. +20% крита, +10% находки, -20 радиации!", "price": 500, "weight": 0.3},
    {"name": "Грааль", "description": "Святой артефакт. Полное восстановление HP и -50 радиации.", "price": 600, "weight": 0.2},
    {"name": "Феникс", "description": "Огненная птица в камне. +30 защиты, иммунитет к огню.", "price": 550, "weight": 0.4},
    {"name": "Вечный", "description": "Не стареет. +50 максимального HP навсегда.", "price": 700, "weight": 0.2},
    {"name": "Золото", "description": "Солнечный артефакт. +30% находки, +15% крита.", "price": 450, "weight": 0.3},
    {"name": "Призрак", "description": "Позволяет уклоняться. +25% уклонения.", "price": 480, "weight": 0.25},
    {"name": "Бездна", "description": "Поглощает радиацию. -50 радиации, +20 энергии.", "price": 520, "weight": 0.3}
  ],
  "other": [
    {"name": "Аптечка", "description": "Медицинский набор. Лечит раны.", "price": 20, "weight": 0.5},
    {"name": "Бинт", "description": "Простой бинт. Можно перевязать раны.", "price": 5, "weight": 0.1},
    {"name": "Антирад", "description": "Препарат против радиации. Выводит радиацию.", "price": 30, "weight": 0.2},
    {"name": "Хлеб", "description": "Чёрствый хлеб. Лучше, чем ничего.", "price": 10, "weight": 0.3},
    {"name": "Тушёнка", "description": "Банка тушёнки. Восстанавливает силы.", "price": 15, "weight": 0.4},
    {"name": "Консервы", "description": "Разные консервы. Сытно.", "price": 12, "weight": 0.35},
    {"name": "Кофе", "description": "Банка кофе. Бодрит.", "price": 8, "weight": 0.25},
    {"name": "Энергетик", "description": "Баночка с энергетиком. Восстанавливает силы.", "price": 10, "weight": 0.25},
    {"name": "Супер энергетик", "description": "Супер энергетик. Полностью восстанавливает энергию.", "price": 50, "weight": 0.3},
    {"name": "Вода", "description": "Бутылка воды. Утоляет жажду.", "price": 5, "weight": 0.5},
    {"name": "Дозиметр", "description": "Прибор для измерения радиации.", "price": 25, "weight": 0.3},
    {"name": "Фонарик", "description": "Поисковый фонарь. Освещает темноту.", "price": 15, "weight": 0.4},
    {"name": "Компас", "description": "Старый компас сталкера. +5% к находкам.", "price": 150, "weight": 0.1},
    {"name": "Рация", "description": "Связь с городом. Связь с торговцами.", "price": 500, "weight": 1.0},
    {"name": "Детектор аномалий", "description": "Базовый прибор. +10% шанс артефакта.", "price": 800, "weight": 0.5},
    {"name": "Эхо-1", "description": "Недорогой детектор. +15% к шансу артефакта.", "price": 1200, "weight": 0.4},
    {"name": "Отклик-М", "description": "Улучшенный детектор. +25% к шансу артефакта.", "price": 2500, "weight": 0.5},
    {"name": "Сканер-П", "description": "Для электромагнитных артефактов. +30%.", "price": 3500, "weight": 0.6},
    {"name": "Пеленг-3", "description": "Профессиональный прибор. +40% к шансу.", "price": 5000, "weight": 0.7},
    {"name": "Гном-Т", "description": "Для гравитационных артефактов. +50%.", "price": 6000, "weight": 1.2},
    {"name": "Детектор-Х", "description": "Экспериментальный. +35%, +60% для редких.", "price": 7500, "weight": 0.5},
    {"name": "Аномалист-2", "description": "Популярный прибор. +45% к шансу.", "price": 6500, "weight": 0.6},
    {"name": "Мираж-Альфа", "description": "Для пси-артефактов. +65%.", "price": 8000, "weight": 0.4},
    {"name": "Око Зоны", "description": "Легендарный детектор. +55%, +80% в скоплении.", "price": 15000, "weight": 0.3}
  ],
  "trash": [
    {"name": "Ржавая гильза", "description": "Стреляная гильза, уже ни на что не годна.", "price": 1, "weight": 0.01},
    {"name": "Сломанный патрон", "description": "Патрон без пороха, можно разобрать.", "price": 1, "weight": 0.01},
    {"name": "Пустая гильза", "description": "Пустая латунная гильза.", "price": 1, "weight": 0.01},
    {"name": "Ржавый болт", "description": "Покрытый ржавчиной болт.", "price": 1, "weight": 0.02},
    {"name": "Грязная тряпка", "description": "Вонючая тряпка.", "price": 2, "weight": 0.05},
    {"name": "Пустая банка", "description": "Пустая консервная банка.", "price": 1, "weight": 0.05},
    {"name": "Пластиковая бутылка", "description": "Пустая пластиковая бутылка.", "price": 1, "weight": 0.03},
    {"name": "Сломанный нож", "description": "Затупившийся ржавый нож.", "price": 5, "weight": 0.15},
    {"name": "Кость", "description": "Чья-то кость.", "price": 3, "weight": 0.15},
    {"name": "Ключ", "description": "Какой-то ключ.", "price": 3, "weight": 0.08}
  ]
}
